{
  "trained_at": "2026-05-08T20:43:04.826716Z",
  "trainer_version": "hybrid-v1",
  "n_total": 1656,
  "n_train": 1325,
  "n_test": 331,
  "test_cutoff": "2025-05-01",
  "feature_columns": [
    "year",
    "odometer",
    "original_msrp",
    "est_wholesale_price",
    "market_asking_price",
    "base_appraised_value",
    "mileage_adjustment_value",
    "days_on_lot",
    "days_since_purchase",
    "sold_year",
    "sold_month",
    "bb_present",
    "bb_base_wholesale_avg",
    "bb_adj_wholesale_avg",
    "bb_adj_wholesale_clean",
    "bb_adj_private_avg",
    "bb_adj_private_clean",
    "bb_adj_retail_avg",
    "bb_adj_retail_clean",
    "bb_adj_trade_in_avg",
    "bb_adj_trade_in_clean",
    "bb_msrp",
    "bb_retail_equipped",
    "bb_wholesale_adjustment",
    "app_appraised_value",
    "app_market_asking_price",
    "app_available_in_market",
    "app_original_available_in_market",
    "app_avg_days_on_market",
    "app_avg_days_supply",
    "app_n_total",
    "app_supply_depletion",
    "body_type_Convertible",
    "body_type_Coupe",
    "body_type_Hatchback",
    "body_type_OTHER",
    "body_type_SUV",
    "body_type_Sedan",
    "body_type_Wagon",
    "body_type_NULL",
    "supplier_name_Alpha One Motors Llc",
    "supplier_name_Atlanta Autos",
    "supplier_name_Audi Tampa",
    "supplier_name_Auto Imports Miami",
    "supplier_name_Bmw Of Sarasota",
    "supplier_name_Bmw Of Southpoint",
    "supplier_name_Brickell Luxury Motors ",
    "supplier_name_Car Drop",
    "supplier_name_Classic Cars Of Palm Beach Llc",
    "supplier_name_Crown Automotive Management Inc Dba Jaguar Land Rover Of St Petersburg",
    "supplier_name_Duval Acura",
    "supplier_name_Duval Honda",
    "supplier_name_Ed Voyles Chrysler Jeep",
    "supplier_name_Elmhurst Acura Kia",
    "supplier_name_Germain Ford Of Beavercreek",
    "supplier_name_Germain Honda Of Beavercreek",
    "supplier_name_Germain Honda Of Naples",
    "supplier_name_Hendrick Lexus Of Northlake",
    "supplier_name_I-75 Autos",
    "supplier_name_Jaguar Land Rover Lakeland",
    "supplier_name_Keffer Volkswagen",
    "supplier_name_Land Rover Orlando",
    "supplier_name_Lifetime Automotive Group",
    "supplier_name_Mall Of Georgia Mazda",
    "supplier_name_Mall Of Georgia Mini",
    "supplier_name_Manheim Orlando",
    "supplier_name_Manheim Palm Beach",
    "supplier_name_Marino Performance Motors",
    "supplier_name_Marshall Goldman Motor Sls & Leasing Llc",
    "supplier_name_Napleton's Goldcoast Imports Inc.",
    "supplier_name_OTHER",
    "supplier_name_Oak Hill Sourcing",
    "supplier_name_Ocean Mazda",
    "supplier_name_Orange County Motorsports Llc D/b/a Jumboluxurycars.com",
    "supplier_name_Parks Chevrolet Huntersville",
    "supplier_name_Rick Hendricks Bmw",
    "supplier_name_Right 1 Auto ",
    "supplier_name_Rountree Moore Kia",
    "supplier_name_Sams Motors International Inc.",
    "supplier_name_Southeast Auto Showroom",
    "supplier_name_Southeast Car Agency",
    "supplier_name_Stevenson-hendrick Honda Wilmington",
    "supplier_name_Tamiami Ford Inc",
    "supplier_name_Texas Direct",
    "supplier_name_Thomasville Toyota",
    "supplier_name_Tom Bush Bmw Orange Park",
    "supplier_name_Toyota Of Vero Beach",
    "supplier_name_Ultimo Northbrook",
    "supplier_name_Ultimo Warrenville",
    "supplier_name_Ultimo Westmont",
    "supplier_name_h Greg Nissan Delray",
    "supplier_name_NULL",
    "sale_type_Retail",
    "sale_type_Wholesale",
    "sale_type_OTHER",
    "sale_type_NULL",
    "vehicle_sale_type_Used",
    "vehicle_sale_type_OTHER",
    "vehicle_sale_type_NULL",
    "model_name_3-Series 330i Sedan",
    "model_name_3-Series M340i Sedan",
    "model_name_4-Series 430i Convertible",
    "model_name_5-Series 530i Sedan",
    "model_name_7-Series 740i Sedan",
    "model_name_7-Series 750i XDrive Sedan",
    "model_name_M3",
    "model_name_M3 Competition Sedan",
    "model_name_M3 Sedan",
    "model_name_M4",
    "model_name_M4 Competition Coupe",
    "model_name_M4 Coupe",
    "model_name_M5 Sedan",
    "model_name_OTHER",
    "model_name_X3",
    "model_name_X3 M40i Sport Utility Vehicle",
    "model_name_X3 SDrive30i Sport Utility Vehicle",
    "model_name_X3 XDrive30i Sport Utility Vehicle",
    "model_name_X4 XDrive30i Sport Utility Vehicle",
    "model_name_X5",
    "model_name_X5 M Sport Utility Vehicle",
    "model_name_X5 XDrive35i Sport Utility Vehicle",
    "model_name_X5 XDrive40i Sport Utility Vehicle",
    "model_name_X5 XDrive50i Sport Utility Vehicle",
    "model_name_X5 xDrive40i Sport Utility Vehicle",
    "model_name_X6 xDrive40i Sport Utility Vehicle",
    "model_name_X7 M50i Sport Utility Vehicle",
    "model_name_X7 M60i Sport Utility Vehicle",
    "model_name_X7 XDrive40i Sport Utility Vehicle",
    "model_name_X7 xDrive40i Sport Utility Vehicle",
    "model_name_i8",
    "model_name_NULL",
    "base_model_2-Series",
    "base_model_3 Series",
    "base_model_3-Series",
    "base_model_4-Series",
    "base_model_5-Series",
    "base_model_6-Series",
    "base_model_7-Series",
    "base_model_8-Series",
    "base_model_Alpina B7",
    "base_model_Bmw",
    "base_model_M-Series M4",
    "base_model_M2",
    "base_model_M3",
    "base_model_M4",
    "base_model_M5",
    "base_model_M6",
    "base_model_M8",
    "base_model_OTHER",
    "base_model_X1",
    "base_model_X2",
    "base_model_X3",
    "base_model_X4",
    "base_model_X5",
    "base_model_X6",
    "base_model_X7",
    "base_model_XM",
    "base_model_Z4",
    "base_model_Z8",
    "base_model_i3",
    "base_model_i8",
    "base_model_iX",
    "base_model_NULL"
  ],
  "categories": {
    "body_type": [
      "SUV",
      "Sedan",
      "Coupe",
      "Convertible",
      "Wagon",
      "Hatchback"
    ],
    "supplier_name": [
      "Mall Of Georgia Mini",
      "Napleton's Goldcoast Imports Inc.",
      "Ed Voyles Chrysler Jeep",
      "Bmw Of Southpoint",
      "Bmw Of Sarasota",
      "I-75 Autos",
      "Ultimo Northbrook",
      "Mall Of Georgia Mazda",
      "Classic Cars Of Palm Beach Llc",
      "Ultimo Westmont",
      "Manheim Orlando",
      "Duval Acura",
      "Right 1 Auto ",
      "Ultimo Warrenville",
      "Oak Hill Sourcing",
      "Texas Direct",
      "Germain Honda Of Naples",
      "Atlanta Autos",
      "h Greg Nissan Delray",
      "Land Rover Orlando",
      "Germain Honda Of Beavercreek",
      "Orange County Motorsports Llc D/b/a Jumboluxurycars.com",
      "Sams Motors International Inc.",
      "Toyota Of Vero Beach",
      "Hendrick Lexus Of Northlake",
      "Crown Automotive Management Inc Dba Jaguar Land Rover Of St Petersburg",
      "Brickell Luxury Motors ",
      "Auto Imports Miami",
      "Lifetime Automotive Group",
      "Southeast Auto Showroom",
      "Parks Chevrolet Huntersville",
      "Manheim Palm Beach",
      "Marino Performance Motors",
      "Audi Tampa",
      "Alpha One Motors Llc",
      "Tamiami Ford Inc",
      "Ocean Mazda",
      "Elmhurst Acura Kia",
      "Marshall Goldman Motor Sls & Leasing Llc",
      "Tom Bush Bmw Orange Park",
      "Rick Hendricks Bmw",
      "Duval Honda",
      "Southeast Car Agency",
      "Thomasville Toyota",
      "Keffer Volkswagen",
      "Jaguar Land Rover Lakeland",
      "Germain Ford Of Beavercreek",
      "Car Drop",
      "Stevenson-hendrick Honda Wilmington",
      "Rountree Moore Kia"
    ],
    "sale_type": [
      "Wholesale",
      "Retail"
    ],
    "vehicle_sale_type": [
      "Used"
    ],
    "model_name": [
      "X5",
      "X7 xDrive40i Sport Utility Vehicle",
      "M3 Sedan",
      "X5 XDrive40i Sport Utility Vehicle",
      "M5 Sedan",
      "X7 XDrive40i Sport Utility Vehicle",
      "M4",
      "X5 xDrive40i Sport Utility Vehicle",
      "M3 Competition Sedan",
      "X3 M40i Sport Utility Vehicle",
      "7-Series 740i Sedan",
      "4-Series 430i Convertible",
      "M4 Coupe",
      "7-Series 750i XDrive Sedan",
      "X7 M50i Sport Utility Vehicle",
      "M3",
      "X3 SDrive30i Sport Utility Vehicle",
      "X6 xDrive40i Sport Utility Vehicle",
      "3-Series 330i Sedan",
      "M4 Competition Coupe",
      "X4 XDrive30i Sport Utility Vehicle",
      "i8",
      "X3",
      "X5 XDrive35i Sport Utility Vehicle",
      "3-Series M340i Sedan",
      "5-Series 530i Sedan",
      "X5 XDrive50i Sport Utility Vehicle",
      "X3 XDrive30i Sport Utility Vehicle",
      "X5 M Sport Utility Vehicle",
      "X7 M60i Sport Utility Vehicle"
    ],
    "base_model": [
      "X5",
      "4-Series",
      "X3",
      "X7",
      "7-Series",
      "M4",
      "5-Series",
      "3-Series",
      "X6",
      "M3",
      "M5",
      "8-Series",
      "6-Series",
      "X4",
      "X1",
      "M8",
      "2-Series",
      "i8",
      "M6",
      "M2",
      "Z4",
      "X2",
      "i3",
      "XM",
      "3 Series",
      "iX",
      "Z8",
      "Alpina B7",
      "M-Series M4",
      "Bmw"
    ]
  },
  "metrics": {
    "mae_dollars": 3167.0,
    "mape_pct": 7.98,
    "r2": 0.9415,
    "within_5pct": 54.7,
    "within_10pct": 81.0
  },
  "baseline_metrics": {
    "mae_dollars": 3493.0,
    "mape_pct": 8.85,
    "ratio": 1.0241
  },
  "top_features": [
    {
      "name": "base_appraised_value",
      "importance": 0.5283176898956299
    },
    {
      "name": "market_asking_price",
      "importance": 0.18494267761707306
    },
    {
      "name": "est_wholesale_price",
      "importance": 0.17065127193927765
    },
    {
      "name": "body_type_Sedan",
      "importance": 0.0042934841476380825
    },
    {
      "name": "odometer",
      "importance": 0.003319298382848501
    },
    {
      "name": "base_model_M4",
      "importance": 0.003230586415156722
    },
    {
      "name": "model_name_M4 Competition Coupe",
      "importance": 0.0032010688446462154
    },
    {
      "name": "body_type_Coupe",
      "importance": 0.002898137317970395
    },
    {
      "name": "days_on_lot",
      "importance": 0.0028230417519807816
    },
    {
      "name": "supplier_name_Ultimo Northbrook",
      "importance": 0.0028188086580485106
    }
  ],
  "make_name": "BMW",
  "tier": "per_make"
}