{
  "make_name": "INFINITI",
  "trained_at": "2026-05-10T08:31:25.572089Z",
  "n_total": 163,
  "n_train": 156,
  "n_test": 7,
  "test_cutoff": "2026-01-01",
  "feature_columns": [
    "year",
    "odometer",
    "original_msrp",
    "est_wholesale_price",
    "market_asking_price",
    "base_appraised_value",
    "mileage_adjustment_value",
    "days_on_lot",
    "days_since_purchase",
    "sold_year",
    "sold_month",
    "model_name_G Convertible",
    "model_name_G Sedan G37 Journey Sedan 4 Dr.",
    "model_name_Infiniti",
    "model_name_OTHER",
    "model_name_Q50",
    "model_name_Q50 LUXE Sedan",
    "model_name_Q50 Luxe Sedan",
    "model_name_Q50 Premium Sedan",
    "model_name_Q50 Red Sport 400 Sedan",
    "model_name_Q50 Red Sport 400 Sedan 4 Dr.",
    "model_name_Q60 Premium Coupe",
    "model_name_Q60 Red Sport 400 Coupe",
    "model_name_QX30 Luxury Sport Utility Vehicle",
    "model_name_QX30 Sport Sport Utility Vehicle",
    "model_name_QX50",
    "model_name_QX50 Essential Sport Utility Vehicle",
    "model_name_QX56 QX56 Wagon 4 Dr.",
    "model_name_QX60",
    "model_name_QX60 AUTOGRAPH Sport Utility Vehicle",
    "model_name_QX60 LUXE Sport Utility Vehicle",
    "model_name_QX60 Lux Sport Utility Vehicle",
    "model_name_QX60 Lux Wagon 4 Dr.",
    "model_name_QX60 Luxe Sport Utility Vehicle",
    "model_name_QX60 Sport Utility Vehicle",
    "model_name_QX60 Wagon 4 Dr.",
    "model_name_QX70",
    "model_name_QX80",
    "model_name_QX80 LUXE Sport Utility Vehicle",
    "model_name_QX80 Limited Sport Utility Vehicle",
    "model_name_QX80 Sport Utility Vehicle",
    "model_name_QX80 Wagon 4 Dr.",
    "model_name_NULL",
    "body_type_Convertible",
    "body_type_Coupe",
    "body_type_OTHER",
    "body_type_SUV",
    "body_type_Sedan",
    "body_type_Wagon",
    "body_type_NULL",
    "supplier_name_Arrigo Chrysler Dodge Jeep Ram Of Margate",
    "supplier_name_Beck Nissan",
    "supplier_name_Bmw Mini South Atlanta",
    "supplier_name_Bmw Of Southpoint",
    "supplier_name_Car Drop",
    "supplier_name_Carmax",
    "supplier_name_Classic Cars Of Palm Beach Llc",
    "supplier_name_Duval Acura",
    "supplier_name_Ed Voyles Chrysler Jeep",
    "supplier_name_Elder Ford Of Tampa Llc",
    "supplier_name_Ferrari Maserati Of Fort Lauderdale",
    "supplier_name_Fort Myers Infiniti",
    "supplier_name_Gainesville Buick Gmc",
    "supplier_name_Germain Ford Of Beavercreek",
    "supplier_name_Germain Honda Of Beavercreek",
    "supplier_name_Gold Coast Motorsports",
    "supplier_name_Hendrick Lexus Of Northlake",
    "supplier_name_Hgreg Lux",
    "supplier_name_Honda Of Lake City",
    "supplier_name_Honda Of Ocala",
    "supplier_name_I-75 Autos",
    "supplier_name_Infiniti Of Coconut Creek",
    "supplier_name_Infiniti Of Orange Park",
    "supplier_name_Kia Of Orange Park",
    "supplier_name_Land Rover Orlando",
    "supplier_name_Lifetime Automotive Group",
    "supplier_name_Luxury Auto Selection",
    "supplier_name_Mall Of Georgia Mazda",
    "supplier_name_Mall Of Georgia Mini",
    "supplier_name_Manheim Orlando",
    "supplier_name_Marshall Goldman Motor Sls & Leasing Llc",
    "supplier_name_Motor Trends Of Houston",
    "supplier_name_Napleton Italian Imports ",
    "supplier_name_Napleton's Arlington Heights Chrysler Dodge Jeep Ram",
    "supplier_name_Napleton's Goldcoast Imports Inc.",
    "supplier_name_Nissan Of Orange Park",
    "supplier_name_Northside Imports",
    "supplier_name_OTHER",
    "supplier_name_Oak Hill Sourcing",
    "supplier_name_Orange County Motorsports Llc D/b/a Jumboluxurycars.com",
    "supplier_name_Rountree Moore Chevrolet",
    "supplier_name_Rountree Moore Kia",
    "supplier_name_Rountree Moore Nissan",
    "supplier_name_Rountree Moore Toyota",
    "supplier_name_Sams Motors International Inc.",
    "supplier_name_Southeast Car Agency",
    "supplier_name_Sz Motorcars",
    "supplier_name_Texas Direct",
    "supplier_name_Thomasville Toyota",
    "supplier_name_Ultimo Westmont",
    "supplier_name_h Greg Nissan Delray",
    "supplier_name_NULL",
    "sale_type_Retail",
    "sale_type_Wholesale",
    "sale_type_OTHER",
    "sale_type_NULL",
    "vehicle_sale_type_Used",
    "vehicle_sale_type_OTHER",
    "vehicle_sale_type_NULL"
  ],
  "categories": {
    "model_name": [
      "QX80 Sport Utility Vehicle",
      "Q50",
      "QX60 Sport Utility Vehicle",
      "QX80 LUXE Sport Utility Vehicle",
      "QX80",
      "QX50",
      "QX60 Wagon 4 Dr.",
      "Q60 Premium Coupe",
      "QX60 Luxe Sport Utility Vehicle",
      "QX80 Wagon 4 Dr.",
      "G Convertible",
      "Q50 LUXE Sedan",
      "QX80 Limited Sport Utility Vehicle",
      "QX60 Lux Sport Utility Vehicle",
      "G Sedan G37 Journey Sedan 4 Dr.",
      "Q50 Premium Sedan",
      "QX30 Luxury Sport Utility Vehicle",
      "QX70",
      "Q50 Red Sport 400 Sedan",
      "Q50 Luxe Sedan",
      "QX60",
      "Q60 Red Sport 400 Coupe",
      "QX30 Sport Sport Utility Vehicle",
      "QX50 Essential Sport Utility Vehicle",
      "Infiniti",
      "QX60 LUXE Sport Utility Vehicle",
      "QX60 AUTOGRAPH Sport Utility Vehicle",
      "QX56 QX56 Wagon 4 Dr.",
      "QX60 Lux Wagon 4 Dr.",
      "Q50 Red Sport 400 Sedan 4 Dr."
    ],
    "body_type": [
      "SUV",
      "Sedan",
      "Wagon",
      "Coupe",
      "Convertible"
    ],
    "supplier_name": [
      "I-75 Autos",
      "Manheim Orlando",
      "Ed Voyles Chrysler Jeep",
      "Texas Direct",
      "h Greg Nissan Delray",
      "Nissan Of Orange Park",
      "Infiniti Of Orange Park",
      "Germain Honda Of Beavercreek",
      "Rountree Moore Nissan",
      "Gainesville Buick Gmc",
      "Classic Cars Of Palm Beach Llc",
      "Southeast Car Agency",
      "Infiniti Of Coconut Creek",
      "Napleton's Goldcoast Imports Inc.",
      "Beck Nissan",
      "Thomasville Toyota",
      "Land Rover Orlando",
      "Lifetime Automotive Group",
      "Mall Of Georgia Mazda",
      "Fort Myers Infiniti",
      "Motor Trends Of Houston",
      "Napleton's Arlington Heights Chrysler Dodge Jeep Ram",
      "Bmw Of Southpoint",
      "Rountree Moore Toyota",
      "Sams Motors International Inc.",
      "Kia Of Orange Park",
      "Duval Acura",
      "Germain Ford Of Beavercreek",
      "Luxury Auto Selection",
      "Northside Imports",
      "Ultimo Westmont",
      "Sz Motorcars",
      "Gold Coast Motorsports",
      "Ferrari Maserati Of Fort Lauderdale",
      "Car Drop",
      "Napleton Italian Imports ",
      "Carmax",
      "Orange County Motorsports Llc D/b/a Jumboluxurycars.com",
      "Arrigo Chrysler Dodge Jeep Ram Of Margate",
      "Elder Ford Of Tampa Llc",
      "Hgreg Lux",
      "Marshall Goldman Motor Sls & Leasing Llc",
      "Mall Of Georgia Mini",
      "Rountree Moore Kia",
      "Honda Of Lake City",
      "Rountree Moore Chevrolet",
      "Bmw Mini South Atlanta",
      "Oak Hill Sourcing",
      "Honda Of Ocala",
      "Hendrick Lexus Of Northlake"
    ],
    "sale_type": [
      "Wholesale",
      "Retail"
    ],
    "vehicle_sale_type": [
      "Used"
    ]
  },
  "metrics": {
    "mae_dollars": 4271.0,
    "mape_pct": 54.19,
    "r2": 0.8304,
    "within_5pct": 28.6,
    "within_10pct": 42.9
  },
  "baseline_metrics": {
    "mae_dollars": 6973.0,
    "mape_pct": 72.04,
    "ratio": 1.0457
  },
  "top_features": [
    {
      "name": "base_appraised_value",
      "importance": 0.35274744033813477
    },
    {
      "name": "est_wholesale_price",
      "importance": 0.3215329945087433
    },
    {
      "name": "market_asking_price",
      "importance": 0.1411600410938263
    },
    {
      "name": "supplier_name_Infiniti Of Orange Park",
      "importance": 0.017945578321814537
    },
    {
      "name": "supplier_name_Mall Of Georgia Mazda",
      "importance": 0.013820192776620388
    },
    {
      "name": "body_type_OTHER",
      "importance": 0.009949947707355022
    },
    {
      "name": "odometer",
      "importance": 0.009920690208673477
    },
    {
      "name": "model_name_QX30 Sport Sport Utility Vehicle",
      "importance": 0.009058964438736439
    }
  ]
}